[
  {
    "businessName": "Padaria Pão Quentinho",
    "ownerName": "Maria Silva",
    "cnae": "4721-1/02 - Padaria",
    "region": "Sudeste",
    "city": "São Paulo",
    "gender": "female",
    "tpv": 65000,
    "avgTicket": 22,
    "salesCount": 2950,
    "onlineShare": 12,
    "storefront": "street",
    "signatureItem": "Pão francês artesanal"
  },
  {
    "businessName": "Auto Center Borges",
    "ownerName": "Carlos Borges",
    "cnae": "4520-0/01 - Oficina Mecânica",
    "region": "Sul",
    "city": "Curitiba",
    "gender": "male",
    "tpv": 90000,
    "avgTicket": 380,
    "salesCount": 720,
    "onlineShare": 8,
    "storefront": "street",
    "signatureItem": "Troca de óleo e revisão rápida"
  },
  {
    "businessName": "Bela Moda Boutique",
    "ownerName": "Ana Paula",
    "cnae": "4781-4/00 - Loja de Roupas",
    "region": "Nordeste",
    "city": "Salvador",
    "gender": "female",
    "tpv": 48000,
    "avgTicket": 160,
    "salesCount": 900,
    "onlineShare": 35,
    "storefront": "mall",
    "signatureItem": "Vestidos leves e coloridos"
  },
  {
    "businessName": "Açaí da Praia",
    "ownerName": "Marcos Antônio",
    "cnae": "5620-1/04 - Açaíteria",
    "region": "Nordeste",
    "city": "Recife",
    "gender": "male",
    "tpv": 32000,
    "avgTicket": 18,
    "salesCount": 1780,
    "onlineShare": 15,
    "storefront": "street",
    "signatureItem": "Açaí com granola e frutas"
  },
  {
    "businessName": "Pizzaria Nonna Rosa",
    "ownerName": "Giuseppe Romano",
    "cnae": "5611-2/03 - Pizzaria",
    "region": "Sudeste",
    "city": "São Paulo",
    "gender": "male",
    "tpv": 125000,
    "avgTicket": 55,
    "salesCount": 2270,
    "onlineShare": 42,
    "storefront": "street",
    "signatureItem": "Pizza margherita no forno a lenha"
  },
  {
    "businessName": "Estúdio Bela Forma",
    "ownerName": "Camila Santos",
    "cnae": "9602-5/04 - Estética e Cosméticos",
    "region": "Sul",
    "city": "Porto Alegre",
    "gender": "female",
    "tpv": 78000,
    "avgTicket": 280,
    "salesCount": 890,
    "onlineShare": 25,
    "storefront": "street",
    "signatureItem": "Massagem relaxante e drenagem"
  },
  {
    "businessName": "CrossFit Iron",
    "ownerName": "Rafael Strongman",
    "cnae": "9319-1/99 - Crossfit",
    "region": "Sudeste",
    "city": "Rio de Janeiro",
    "gender": "male",
    "tpv": 95000,
    "avgTicket": 180,
    "salesCount": 540,
    "onlineShare": 35,
    "storefront": "street",
    "signatureItem": "Treino funcional personalizado"
  },
  {
    "businessName": "Hambúrguer & Cia",
    "ownerName": "Tatiane Costa",
    "cnae": "5620-1/05 - Hamburgueria",
    "region": "Centro-Oeste",
    "city": "Goiânia",
    "gender": "female",
    "tpv": 87000,
    "avgTicket": 35,
    "salesCount": 2480,
    "onlineShare": 55,
    "storefront": "food_truck",
    "signatureItem": "Hambúrguer artesanal com batata rústica"
  },
  {
    "businessName": "Sorveteria Gelato Fino",
    "ownerName": "Antônio Gelatti",
    "cnae": "5611-2/04 - Sorveteria",
    "region": "Sul",
    "city": "Florianópolis",
    "gender": "male",
    "tpv": 42000,
    "avgTicket": 25,
    "salesCount": 1680,
    "onlineShare": 8,
    "storefront": "street",
    "signatureItem": "Gelato artesanal sabor pistache"
  },
  {
    "businessName": "Consultório Dra. Fernanda",
    "ownerName": "Fernanda Medeiros",
    "cnae": "8630-5/03 - Fisioterapia",
    "region": "Nordeste",
    "city": "Fortaleza",
    "gender": "female",
    "tpv": 65000,
    "avgTicket": 120,
    "salesCount": 540,
    "onlineShare": 20,
    "storefront": "medical",
    "signatureItem": "Fisioterapia ortopédica e RPG"
  },
  {
    "businessName": "Livraria Saber & Cultura",
    "ownerName": "Professor João",
    "cnae": "4757-1/00 - Loja de Livros",
    "region": "Norte",
    "city": "Belém",
    "gender": "male",
    "tpv": 38000,
    "avgTicket": 45,
    "salesCount": 845,
    "onlineShare": 30,
    "storefront": "street",
    "signatureItem": "Literatura brasileira e livros técnicos"
  },
  {
    "businessName": "Tapiocaria da Vovó",
    "ownerName": "Severina Oliveira",
    "cnae": "5620-1/06 - Tapiocaria",
    "region": "Nordeste",
    "city": "João Pessoa",
    "gender": "female",
    "tpv": 28000,
    "avgTicket": 12,
    "salesCount": 2330,
    "onlineShare": 5,
    "storefront": "street",
    "signatureItem": "Tapioca de queijo coalho com carne seca"
  },
  {
    "businessName": "Joalheria Diamante",
    "ownerName": "Rodrigo Brilhante",
    "cnae": "4789-0/06 - Joalheria",
    "region": "Sudeste",
    "city": "Belo Horizonte",
    "gender": "male",
    "tpv": 180000,
    "avgTicket": 850,
    "salesCount": 210,
    "onlineShare": 40,
    "storefront": "mall",
    "signatureItem": "Alianças de ouro personalizadas"
  },
  {
    "businessName": "Confeitaria Doce Mel",
    "ownerName": "Isabella Cardoso",
    "cnae": "5611-2/05 - Confeitaria",
    "region": "Sudeste",
    "city": "Campinas",
    "gender": "female",
    "tpv": 52000,
    "avgTicket": 68,
    "salesCount": 765,
    "onlineShare": 25,
    "storefront": "street",
    "signatureItem": "Bolos decorados e doces finos"
  },
  {
    "businessName": "Academia Fitness Plus",
    "ownerName": "Márcio Strength",
    "cnae": "9329-8/01 - Academia de Ginástica",
    "region": "Centro-Oeste",
    "city": "Brasília",
    "gender": "male",
    "tpv": 110000,
    "avgTicket": 95,
    "salesCount": 1160,
    "onlineShare": 15,
    "storefront": "commercial",
    "signatureItem": "Musculação e aulas de spinning"
  },
  {
    "businessName": "Loja Mundo Kids",
    "ownerName": "Patricia Lima",
    "cnae": "4789-0/10 - Loja de Brinquedos",
    "region": "Norte",
    "city": "Manaus",
    "gender": "female",
    "tpv": 73000,
    "avgTicket": 85,
    "salesCount": 860,
    "onlineShare": 45,
    "storefront": "mall",
    "signatureItem": "Brinquedos educativos e jogos"
  },
  {
    "businessName": "Distribuidora Sabor Doce",
    "ownerName": "Eduardo Pacheco",
    "cnae": "4637-1/01 - Distribuidora de Doces",
    "region": "Sul",
    "city": "Caxias do Sul",
    "gender": "male",
    "tpv": 195000,
    "avgTicket": 420,
    "salesCount": 465,
    "onlineShare": 60,
    "storefront": "warehouse",
    "signatureItem": "Chocolates e doces regionais"
  },
  {
    "businessName": "Escola Pequenos Gênios",
    "ownerName": "Professora Ana Lucia",
    "cnae": "8511-2/00 - Escola Particular",
    "region": "Sudeste",
    "city": "Santos",
    "gender": "female",
    "tpv": 145000,
    "avgTicket": 680,
    "salesCount": 210,
    "onlineShare": 10,
    "storefront": "institutional",
    "signatureItem": "Educação infantil personalizada"
  },
  {
    "businessName": "Informática Total",
    "ownerName": "Lucas Tech",
    "cnae": "4789-0/09 - Loja de Informática",
    "region": "Centro-Oeste",
    "city": "Campo Grande",
    "gender": "male",
    "tpv": 98000,
    "avgTicket": 380,
    "salesCount": 260,
    "onlineShare": 65,
    "storefront": "commercial",
    "signatureItem": "Notebooks e assistência técnica"
  },
  {
    "businessName": "Perfumaria Essência",
    "ownerName": "Mariana Flores",
    "cnae": "4789-0/03 - Loja de Perfumes",
    "region": "Nordeste",
    "city": "Natal",
    "gender": "female",
    "tpv": 67000,
    "avgTicket": 95,
    "salesCount": 705,
    "onlineShare": 35,
    "storefront": "mall",
    "signatureItem": "Perfumes importados e nacionais"
  },
  {
    "businessName": "Sushi Sakura",
    "ownerName": "Takeshi Yamamoto",
    "cnae": "5611-2/07 - Restaurante Japonês",
    "region": "Sudeste",
    "city": "São Paulo",
    "gender": "male",
    "tpv": 156000,
    "avgTicket": 78,
    "salesCount": 2000,
    "onlineShare": 35,
    "storefront": "street",
    "signatureItem": "Sushi fresh e temaki especial"
  },
  {
    "businessName": "Farmácia Popular",
    "ownerName": "Doutora Beatriz",
    "cnae": "4771-7/01 - Farmácia",
    "region": "Norte",
    "city": "Palmas",
    "gender": "female",
    "tpv": 230000,
    "avgTicket": 45,
    "salesCount": 5110,
    "onlineShare": 20,
    "storefront": "street",
    "signatureItem": "Medicamentos e produtos de saúde"
  },
  {
    "businessName": "Lavanderia Express",
    "ownerName": "Dona Rosa",
    "cnae": "9601-7/01 - Lavanderia",
    "region": "Nordeste",
    "city": "Maceió",
    "gender": "female",
    "tpv": 38000,
    "avgTicket": 25,
    "salesCount": 1520,
    "onlineShare": 10,
    "storefront": "street",
    "signatureItem": "Lavagem e passadoria expressa"
  },
  {
    "businessName": "Pet Shop Amigo Fiel",
    "ownerName": "Veterinário Pedro",
    "cnae": "4789-0/08 - Pet Shop",
    "region": "Sul",
    "city": "Londrina",
    "gender": "male",
    "tpv": 95000,
    "avgTicket": 85,
    "salesCount": 1118,
    "onlineShare": 30,
    "storefront": "street",
    "signatureItem": "Ração premium e banho & tosa"
  },
  {
    "businessName": "Ótica Visão Clara",
    "ownerName": "Dr. Henrique",
    "cnae": "4789-0/04 - Ótica",
    "region": "Centro-Oeste",
    "city": "Cuiabá",
    "gender": "male",
    "tpv": 120000,
    "avgTicket": 320,
    "salesCount": 375,
    "onlineShare": 25,
    "storefront": "commercial",
    "signatureItem": "Óculos de grau e lentes de contato"
  },
  {
    "businessName": "Floricultura Jardim",
    "ownerName": "Valentina Pétalas",
    "cnae": "4789-0/12 - Floricultura",
    "region": "Sul",
    "city": "Pelotas",
    "gender": "female",
    "tpv": 42000,
    "avgTicket": 55,
    "salesCount": 764,
    "onlineShare": 40,
    "storefront": "street",
    "signatureItem": "Arranjos florais e plantas ornamentais"
  },
  {
    "businessName": "Marcenaria Madeira Nobre",
    "ownerName": "Mestre Sebastião",
    "cnae": "1623-9/01 - Marcenaria",
    "region": "Norte",
    "city": "Macapá",
    "gender": "male",
    "tpv": 78000,
    "avgTicket": 650,
    "salesCount": 120,
    "onlineShare": 15,
    "storefront": "workshop",
    "signatureItem": "Móveis planejados em madeira de lei"
  },
  {
    "businessName": "Clínica Sorriso Perfeito",
    "ownerName": "Dra. Odontóloga Carla",
    "cnae": "8630-5/01 - Odontologia",
    "region": "Sudeste",
    "city": "Vitória",
    "gender": "female",
    "tpv": 145000,
    "avgTicket": 180,
    "salesCount": 806,
    "onlineShare": 22,
    "storefront": "medical",
    "signatureItem": "Ortodontia e implantes dentários"
  },
  {
    "businessName": "Salão Glamour",
    "ownerName": "Cabeleireira Juliana",
    "cnae": "9602-5/01 - Salão de Beleza",
    "region": "Nordeste",
    "city": "Aracaju",
    "gender": "female",
    "tpv": 68000,
    "avgTicket": 85,
    "salesCount": 800,
    "onlineShare": 15,
    "storefront": "street",
    "signatureItem": "Corte, escova e coloração profissional"
  },
  {
    "businessName": "Lanchonete Do Seu Zé",
    "ownerName": "José Maria",
    "cnae": "5620-1/03 - Lanchonete",
    "region": "Centro-Oeste",
    "city": "Anápolis",
    "gender": "male",
    "tpv": 45000,
    "avgTicket": 18,
    "salesCount": 2500,
    "onlineShare": 8,
    "storefront": "street",
    "signatureItem": "X-salada e suco natural"
  },
  {
    "businessName": "Loja de Calçados Passo Certo",
    "ownerName": "Empresária Mônica",
    "cnae": "4782-2/01 - Loja de Calçados",
    "region": "Sul",
    "city": "Blumenau",
    "gender": "female",
    "tpv": 112000,
    "avgTicket": 140,
    "salesCount": 800,
    "onlineShare": 45,
    "storefront": "mall",
    "signatureItem": "Sapatos femininos e masculinos"
  },
  {
    "businessName": "Oficina Moto Speed",
    "ownerName": "Mecânico Wagner",
    "cnae": "4520-0/03 - Oficina de Motos",
    "region": "Norte",
    "city": "Rio Branco",
    "gender": "male",
    "tpv": 65000,
    "avgTicket": 180,
    "salesCount": 361,
    "onlineShare": 12,
    "storefront": "street",
    "signatureItem": "Revisão e peças para motos"
  },
  {
    "businessName": "Padaria Pão & Café",
    "ownerName": "Seu Francisco",
    "cnae": "4721-1/02 - Padaria",
    "region": "Nordeste",
    "city": "Teresina",
    "gender": "male",
    "tpv": 58000,
    "avgTicket": 15,
    "salesCount": 3867,
    "onlineShare": 5,
    "storefront": "street",
    "signatureItem": "Pão de açúcar e café expresso"
  },
  {
    "businessName": "Consultório Psicológico Mente Sã",
    "ownerName": "Psicóloga Amanda",
    "cnae": "8630-5/04 - Psicologia",
    "region": "Sudeste",
    "city": "Juiz de Fora",
    "gender": "female",
    "tpv": 72000,
    "avgTicket": 150,
    "salesCount": 480,
    "onlineShare": 30,
    "storefront": "medical",
    "signatureItem": "Terapia cognitivo-comportamental"
  },
  {
    "businessName": "Açougue Carne Premium",
    "ownerName": "Açougueiro Roberto",
    "cnae": "4722-9/01 - Açougue",
    "region": "Centro-Oeste",
    "city": "Rondonópolis",
    "gender": "male",
    "tpv": 89000,
    "avgTicket": 45,
    "salesCount": 1978,
    "onlineShare": 12,
    "storefront": "street",
    "signatureItem": "Carnes nobres e linguiças artesanais"
  },
  {
    "businessName": "Autoescola Direção Segura",
    "ownerName": "Instrutor Miguel",
    "cnae": "8549-2/00 - Autoescola",
    "region": "Sul",
    "city": "Joinville",
    "gender": "male",
    "tpv": 156000,
    "avgTicket": 1200,
    "salesCount": 130,
    "onlineShare": 20,
    "storefront": "commercial",
    "signatureItem": "Habilitação categoria B e A"
  },
  {
    "businessName": "Papelaria Estudante",
    "ownerName": "Professora Marta",
    "cnae": "4789-0/07 - Papelaria",
    "region": "Norte",
    "city": "Boa Vista",
    "gender": "female",
    "tpv": 34000,
    "avgTicket": 28,
    "salesCount": 1214,
    "onlineShare": 25,
    "storefront": "street",
    "signatureItem": "Material escolar e papelaria"
  },
  {
    "businessName": "Hamburgeria Artesanal Brothers",
    "ownerName": "Chef Bruno",
    "cnae": "5620-1/05 - Hamburgueria",
    "region": "Sudeste",
    "city": "Sorocaba",
    "gender": "male",
    "tpv": 98000,
    "avgTicket": 42,
    "salesCount": 2333,
    "onlineShare": 55,
    "storefront": "street",
    "signatureItem": "Burger gourmet com molho especial"
  },
  {
    "businessName": "Barbearia Vintage",
    "ownerName": "Barbeiro Fábio",
    "cnae": "9602-5/02 - Barbearia",
    "region": "Nordeste",
    "city": "Caruaru",
    "gender": "male",
    "tpv": 42000,
    "avgTicket": 35,
    "salesCount": 1200,
    "onlineShare": 10,
    "storefront": "street",
    "signatureItem": "Corte clássico e barba feita"
  },
  {
    "businessName": "Loja de Instrumentos Música & Arte",
    "ownerName": "Maestro Antônio",
    "cnae": "4789-0/11 - Loja de Instrumentos",
    "region": "Centro-Oeste",
    "city": "Dourados",
    "gender": "male",
    "tpv": 78000,
    "avgTicket": 380,
    "salesCount": 205,
    "onlineShare": 35,
    "storefront": "street",
    "signatureItem": "Violões e teclados musicais"
  },
  {
    "businessName": "Clínica Veterinária Bichos & Cia",
    "ownerName": "Veterinária Lívia",
    "cnae": "7500-1/00 - Clínica Veterinária",
    "region": "Sul",
    "city": "Passo Fundo",
    "gender": "female",
    "tpv": 125000,
    "avgTicket": 120,
    "salesCount": 1042,
    "onlineShare": 25,
    "storefront": "medical",
    "signatureItem": "Consultas e cirurgias veterinárias"
  },
  {
    "businessName": "Chocolateria Cacau Premium",
    "ownerName": "Chocolatier Patrícia",
    "cnae": "5611-2/05 - Confeitaria",
    "region": "Sudeste",
    "city": "Petrópolis",
    "gender": "female",
    "tpv": 89000,
    "avgTicket": 75,
    "salesCount": 1187,
    "onlineShare": 40,
    "storefront": "street",
    "signatureItem": "Chocolates belgas artesanais"
  },
  {
    "businessName": "Loja de Móveis Casa Bela",
    "ownerName": "Designer Isabel",
    "cnae": "4759-8/01 - Loja de Móveis",
    "region": "Norte",
    "city": "Porto Velho",
    "gender": "female",
    "tpv": 234000,
    "avgTicket": 850,
    "salesCount": 275,
    "onlineShare": 30,
    "storefront": "commercial",
    "signatureItem": "Móveis planejados e decoração"
  },
  {
    "businessName": "Padaria Grãos Dourados",
    "ownerName": "Padeiro João Carlos",
    "cnae": "4721-1/02 - Padaria",
    "region": "Nordeste",
    "city": "Mossoró",
    "gender": "male",
    "tpv": 67000,
    "avgTicket": 20,
    "salesCount": 3350,
    "onlineShare": 8,
    "storefront": "street",
    "signatureItem": "Pão integral e bolos caseiros"
  },
  {
    "businessName": "Studio de Tatuagem Ink Art",
    "ownerName": "Tatuador Rodrigo",
    "cnae": "9609-2/06 - Studio de Tatuagem",
    "region": "Sul",
    "city": "Santa Maria",
    "gender": "male",
    "tpv": 78000,
    "avgTicket": 280,
    "salesCount": 279,
    "onlineShare": 40,
    "storefront": "street",
    "signatureItem": "Tatuagens realistas e tribais"
  },
  {
    "businessName": "Supermercado Economia",
    "ownerName": "Gerente Antônia",
    "cnae": "4711-3/02 - Supermercado",
    "region": "Centro-Oeste",
    "city": "Várzea Grande",
    "gender": "female",
    "tpv": 456000,
    "avgTicket": 65,
    "salesCount": 7015,
    "onlineShare": 15,
    "storefront": "commercial",
    "signatureItem": "Produtos alimentícios e higiene"
  },
  {
    "businessName": "Escola de Dança Ritmo & Movimento",
    "ownerName": "Coreógrafa Daniela",
    "cnae": "8592-9/01 - Escola de Dança",
    "region": "Sudeste",
    "city": "Ribeirão Preto",
    "gender": "female",
    "tpv": 52000,
    "avgTicket": 120,
    "salesCount": 433,
    "onlineShare": 25,
    "storefront": "studio",
    "signatureItem": "Aulas de ballet e dança contemporânea"
  },
  {
    "businessName": "Pizzaria Massa Italiana",
    "ownerName": "Chef Marco",
    "cnae": "5611-2/03 - Pizzaria",
    "region": "Norte",
    "city": "Santarém",
    "gender": "male",
    "tpv": 89000,
    "avgTicket": 38,
    "salesCount": 2342,
    "onlineShare": 45,
    "storefront": "street",
    "signatureItem": "Pizza calabresa com borda recheada"
  },
  {
    "businessName": "Clínica de Fisioterapia Movimento Livre",
    "ownerName": "Fisioterapeuta Carlos",
    "cnae": "8630-5/03 - Fisioterapia",
    "region": "Nordeste",
    "city": "Campina Grande",
    "gender": "male",
    "tpv": 98000,
    "avgTicket": 85,
    "salesCount": 1153,
    "onlineShare": 20,
    "storefront": "medical",
    "signatureItem": "RPG e fisioterapia esportiva"
  },
  {
    "businessName": "Farmácia e Drogaria Saúde Total",
    "ownerName": "Farmacêutica Ana",
    "cnae": "4771-7/01 - Farmácia",
    "region": "Sul",
    "city": "Canoas",
    "gender": "female",
    "tpv": 189000,
    "avgTicket": 42,
    "salesCount": 4500,
    "onlineShare": 18,
    "storefront": "street",
    "signatureItem": "Medicamentos e suplementos"
  },
  {
    "businessName": "Oficina Multimarcas do João",
    "ownerName": "Mecânico João Batista",
    "cnae": "4520-0/01 - Oficina Mecânica",
    "region": "Centro-Oeste",
    "city": "Rio Verde",
    "gender": "male",
    "tpv": 134000,
    "avgTicket": 420,
    "salesCount": 319,
    "onlineShare": 10,
    "storefront": "street",
    "signatureItem": "Reparo automotivo e pintura"
  },
  {
    "businessName": "Loja de Esportes Atleta Pro",
    "ownerName": "Ex-atleta Fernando",
    "cnae": "4763-6/03 - Loja de Esportes",
    "region": "Sudeste",
    "city": "São José dos Campos",
    "gender": "male",
    "tpv": 156000,
    "avgTicket": 95,
    "salesCount": 1642,
    "onlineShare": 50,
    "storefront": "mall",
    "signatureItem": "Tênis esportivos e suplementos"
  },
  {
    "businessName": "Pousada Vista do Mar",
    "ownerName": "Hoteleira Marina",
    "cnae": "5510-8/02 - Pousada",
    "region": "Norte",
    "city": "Parintins",
    "gender": "female",
    "tpv": 123000,
    "avgTicket": 180,
    "salesCount": 683,
    "onlineShare": 60,
    "storefront": "hotel",
    "signatureItem": "Hospedagem com café da manhã"
  },
  {
    "businessName": "Serralheria Ferro & Arte",
    "ownerName": "Serralheiro Nelson",
    "cnae": "2511-0/00 - Serralheria",
    "region": "Nordeste",
    "city": "Feira de Santana",
    "gender": "male",
    "tpv": 89000,
    "avgTicket": 380,
    "salesCount": 234,
    "onlineShare": 15,
    "storefront": "workshop",
    "signatureItem": "Portões e estruturas metálicas"
  },
  {
    "businessName": "Laboratório de Análises Precisão",
    "ownerName": "Biomédica Luciana",
    "cnae": "8630-5/05 - Laboratório",
    "region": "Sul",
    "city": "Maringá",
    "gender": "female",
    "tpv": 234000,
    "avgTicket": 85,
    "salesCount": 2753,
    "onlineShare": 25,
    "storefront": "medical",
    "signatureItem": "Exames clínicos e laboratoriais"
  },
  {
    "businessName": "Casa de Carnes Boi Gordo",
    "ownerName": "Açougueiro Valdir",
    "cnae": "4722-9/01 - Açougue",
    "region": "Centro-Oeste",
    "city": "Sinop",
    "gender": "male",
    "tpv": 112000,
    "avgTicket": 56,
    "salesCount": 2000,
    "onlineShare": 8,
    "storefront": "street",
    "signatureItem": "Churrasco e carnes especiais"
  },
  {
    "businessName": "Creche Pequenos Anjinhos",
    "ownerName": "Educadora Sônia",
    "cnae": "8511-2/01 - Creche",
    "region": "Sudeste",
    "city": "Taubaté",
    "gender": "female",
    "tpv": 98000,
    "avgTicket": 450,
    "salesCount": 218,
    "onlineShare": 5,
    "storefront": "institutional",
    "signatureItem": "Educação infantil integral"
  },
  {
    "businessName": "Taxi Aéreo Voo Seguro",
    "ownerName": "Piloto Roberto",
    "cnae": "5110-2/00 - Taxi Aéreo",
    "region": "Norte",
    "city": "Cruzeiro do Sul",
    "gender": "male",
    "tpv": 345000,
    "avgTicket": 1200,
    "salesCount": 288,
    "onlineShare": 70,
    "storefront": "airport",
    "signatureItem": "Voos regionais e turísticos"
  },
  {
    "businessName": "Churrascaria Tradição Gaúcha",
    "ownerName": "Churrasqueiro Gaúcho",
    "cnae": "5611-2/01 - Churrascaria",
    "region": "Sul",
    "city": "Uruguaiana",
    "gender": "male",
    "tpv": 234000,
    "avgTicket": 68,
    "salesCount": 3441,
    "onlineShare": 25,
    "storefront": "restaurant",
    "signatureItem": "Rodízio de carnes e buffet"
  },
  {
    "businessName": "Loja de Telefonia Connect",
    "ownerName": "Empresário Digital Alan",
    "cnae": "4789-0/13 - Loja de Celulares",
    "region": "Nordeste",
    "city": "Imperatriz",
    "gender": "male",
    "tpv": 189000,
    "avgTicket": 420,
    "salesCount": 450,
    "onlineShare": 65,
    "storefront": "mall",
    "signatureItem": "Smartphones e acessórios"
  },
  {
    "businessName": "Clínica de Nutrição Vida Saudável",
    "ownerName": "Nutricionista Raquel",
    "cnae": "8630-5/06 - Nutrição",
    "region": "Centro-Oeste",
    "city": "Cáceres",
    "gender": "female",
    "tpv": 67000,
    "avgTicket": 120,
    "salesCount": 558,
    "onlineShare": 30,
    "storefront": "medical",
    "signatureItem": "Planos alimentares personalizados"
  },
  {
    "businessName": "Transportadora Carga Expressa",
    "ownerName": "Transportador Edson",
    "cnae": "4930-2/01 - Transportadora",
    "region": "Sudeste",
    "city": "Uberlândia",
    "gender": "male",
    "tpv": 456000,
    "avgTicket": 890,
    "salesCount": 512,
    "onlineShare": 40,
    "storefront": "warehouse",
    "signatureItem": "Transporte de cargas pesadas"
  },
  {
    "businessName": "Doceria Doce Encanto",
    "ownerName": "Doceira Carmelita",
    "cnae": "5611-2/05 - Confeitaria",
    "region": "Norte",
    "city": "Itaituba",
    "gender": "female",
    "tpv": 45000,
    "avgTicket": 32,
    "salesCount": 1406,
    "onlineShare": 20,
    "storefront": "street",
    "signatureItem": "Brigadeiros gourmet e doces finos"
  },
  {
    "businessName": "Loja de Roupas Fashion Week",
    "ownerName": "Estilista Viviane",
    "cnae": "4781-4/00 - Loja de Roupas",
    "region": "Sul",
    "city": "Chapecó",
    "gender": "female",
    "tpv": 123000,
    "avgTicket": 135,
    "salesCount": 911,
    "onlineShare": 55,
    "storefront": "mall",
    "signatureItem": "Moda feminina jovem e casual"
  },
  {
    "businessName": "Oficina de Bicicletas Speed Bike",
    "ownerName": "Ciclista Juliano",
    "cnae": "4789-0/14 - Loja de Bicicletas",
    "region": "Nordeste",
    "city": "Sobral",
    "gender": "male",
    "tpv": 67000,
    "avgTicket": 180,
    "salesCount": 372,
    "onlineShare": 30,
    "storefront": "street",
    "signatureItem": "Bicicletas mountain bike e speed"
  },
  {
    "businessName": "Centro de Estética Beleza Pura",
    "ownerName": "Esteticista Silvia",
    "cnae": "9602-5/04 - Estética e Cosméticos",
    "region": "Centro-Oeste",
    "city": "Primavera do Leste",
    "gender": "female",
    "tpv": 89000,
    "avgTicket": 150,
    "salesCount": 593,
    "onlineShare": 35,
    "storefront": "clinic",
    "signatureItem": "Limpeza de pele e massagens"
  },
  {
    "businessName": "Lanchonete da Esquina",
    "ownerName": "Lancheiro Osvaldo",
    "cnae": "5620-1/03 - Lanchonete",
    "region": "Sudeste",
    "city": "Franca",
    "gender": "male",
    "tpv": 52000,
    "avgTicket": 22,
    "salesCount": 2364,
    "onlineShare": 12,
    "storefront": "street",
    "signatureItem": "Sanduíches naturais e vitaminas"
  },
  {
    "businessName": "Assistência Técnica TechFix",
    "ownerName": "Técnico Leonardo",
    "cnae": "9511-8/00 - Assistência Técnica",
    "region": "Norte",
    "city": "Araguaína",
    "gender": "male",
    "tpv": 78000,
    "avgTicket": 95,
    "salesCount": 821,
    "onlineShare": 45,
    "storefront": "commercial",
    "signatureItem": "Conserto de smartphones e notebooks"
  },
  {
    "businessName": "Studio de Pilates Equilíbrio",
    "ownerName": "Instrutora Fernanda",
    "cnae": "9319-1/01 - Studio de Pilates",
    "region": "Sul",
    "city": "Rio Grande",
    "gender": "female",
    "tpv": 67000,
    "avgTicket": 85,
    "salesCount": 788,
    "onlineShare": 25,
    "storefront": "studio",
    "signatureItem": "Pilates clínico e solo"
  },
  {
    "businessName": "Restaurante Tempero Mineiro",
    "ownerName": "Cozinheira Marlene",
    "cnae": "5611-2/02 - Restaurante",
    "region": "Sudeste",
    "city": "Montes Claros",
    "gender": "female",
    "tpv": 98000,
    "avgTicket": 28,
    "salesCount": 3500,
    "onlineShare": 20,
    "storefront": "street",
    "signatureItem": "Comida mineira caseira e prato feito"
  },
  {
    "businessName": "Frutaria Sabores Naturais",
    "ownerName": "Fruteiro Ademir",
    "cnae": "4724-5/00 - Frutaria",
    "region": "Nordeste",
    "city": "Juazeiro",
    "gender": "male",
    "tpv": 43000,
    "avgTicket": 25,
    "salesCount": 1720,
    "onlineShare": 10,
    "storefront": "street",
    "signatureItem": "Frutas tropicais e sucos naturais"
  },
  {
    "businessName": "Marmoraria Pedra Nobre",
    "ownerName": "Marmorista Claudinei",
    "cnae": "2391-5/01 - Marmoraria",
    "region": "Centro-Oeste",
    "city": "Três Lagoas",
    "gender": "male",
    "tpv": 156000,
    "avgTicket": 980,
    "salesCount": 159,
    "onlineShare": 25,
    "storefront": "workshop",
    "signatureItem": "Bancadas e pias em mármore"
  },
  {
    "businessName": "Escola de Idiomas Global English",
    "ownerName": "Professora Bilingue Sarah",
    "cnae": "8593-7/00 - Escola de Idiomas",
    "region": "Sul",
    "city": "Criciúma",
    "gender": "female",
    "tpv": 89000,
    "avgTicket": 250,
    "salesCount": 356,
    "onlineShare": 40,
    "storefront": "educational",
    "signatureItem": "Inglês conversação e business"
  },
  {
    "businessName": "Gráfica Impressão Digital",
    "ownerName": "Gráfico Hermes",
    "cnae": "1813-0/01 - Gráfica",
    "region": "Sudeste",
    "city": "Governador Valadares",
    "gender": "male",
    "tpv": 123000,
    "avgTicket": 180,
    "salesCount": 683,
    "onlineShare": 50,
    "storefront": "commercial",
    "signatureItem": "Impressão digital e sinalização"
  },
  {
    "businessName": "Casa de Sucos Tropical",
    "ownerName": "Fruticultor Benedito",
    "cnae": "5620-1/07 - Casa de Sucos",
    "region": "Norte",
    "city": "Marabá",
    "gender": "male",
    "tpv": 38000,
    "avgTicket": 15,
    "salesCount": 2533,
    "onlineShare": 8,
    "storefront": "street",
    "signatureItem": "Sucos tropicais e vitaminas"
  },
  {
    "businessName": "Loja de Artesanato Regional",
    "ownerName": "Artesã Conceição",
    "cnae": "4789-0/15 - Loja de Artesanato",
    "region": "Nordeste",
    "city": "Petrolina",
    "gender": "female",
    "tpv": 34000,
    "avgTicket": 45,
    "salesCount": 756,
    "onlineShare": 30,
    "storefront": "street",
    "signatureItem": "Artesanato regional e souvenirs"
  },
  {
    "businessName": "Clínica de Acupuntura Medicina Oriental",
    "ownerName": "Acupunturista Dr. Chang",
    "cnae": "8630-5/07 - Acupuntura",
    "region": "Centro-Oeste",
    "city": "Corumbá",
    "gender": "male",
    "tpv": 78000,
    "avgTicket": 120,
    "salesCount": 650,
    "onlineShare": 35,
    "storefront": "clinic",
    "signatureItem": "Acupuntura e medicina chinesa"
  },
  {
    "businessName": "Video Locadora Cine Nostalgia",
    "ownerName": "Cinéfilo Ademar",
    "cnae": "7722-2/00 - Locadora",
    "region": "Sul",
    "city": "Bagé",
    "gender": "male",
    "tpv": 23000,
    "avgTicket": 12,
    "salesCount": 1917,
    "onlineShare": 5,
    "storefront": "street",
    "signatureItem": "Filmes clássicos e lançamentos"
  },
  {
    "businessName": "Consultório Jurídico Advocacia Total",
    "ownerName": "Advogada Dra. Cláudia",
    "cnae": "6911-7/01 - Escritório de Advocacia",
    "region": "Sudeste",
    "city": "Ipatinga",
    "gender": "female",
    "tpv": 156000,
    "avgTicket": 850,
    "salesCount": 184,
    "onlineShare": 40,
    "storefront": "office",
    "signatureItem": "Direito civil e trabalhista"
  },
  {
    "businessName": "Borracharia Express Pneus",
    "ownerName": "Borracheiro Edvaldo",
    "cnae": "4520-0/04 - Borracharia",
    "region": "Norte",
    "city": "Castanhal",
    "gender": "male",
    "tpv": 67000,
    "avgTicket": 95,
    "salesCount": 705,
    "onlineShare": 15,
    "storefront": "street",
    "signatureItem": "Pneus novos e recauchutados"
  }
]